thinker/__init__.py
thinker/combine.py
thinker/enum_defines.py
thinker/generate_report.py
thinker/graph_serialize.py
thinker/load_model.py
thinker/save_model.py
thinker/tpacker.py
thinker/executor/bin/libthinker.so
thinker/executor/core/operator_attrs.h
thinker/executor/include/thinker/thinker.h
thinker/executor/include/thinker/thinker_status.h
thinker/executor/include/thinker/thinker_type.h
thinker/graph/Graph.py
thinker/graph/GraphEntry.py
thinker/graph/GraphEntryExt.py
thinker/graph/GraphNode.py
thinker/graph/Tensor.py
thinker/graph/__init__.py
thinker/graph/indexed.py
thinker/graph_optimizer/__init__.py
thinker/graph_optimizer/graph_optimizer.py
thinker/graph_optimizer/layout_convert.py
thinker/graph_optimizer/op_divide.py
thinker/graph_optimizer/op_fusion.py
thinker/graph_optimizer/op_replace.py
thinker/graph_optimizer/op_split.py
thinker/graph_optimizer/simple_fusion/__init__.py
thinker/graph_optimizer/simple_fusion/methods.py
thinker/graph_optimizer/simple_fusion/sim_fusion.py
thinker/resource_packer/__init__.py
thinker/resource_packer/memory.py
thinker/resource_packer/venus.py
thinker/resource_packer/_type/__init__.py
thinker/resource_packer/_type/_crc24.py
thinker/resource_packer/_type/_ctype.py
thinker/resource_packer/_type/_tDMA.py
thinker/resource_packer/_type/_tDebug.py
thinker/resource_packer/_type/_tIO.py
thinker/resource_packer/_type/_tMemory.py
thinker/resource_packer/_type/_tModel.py
thinker/resource_packer/_type/_tOperator.py
thinker/resource_packer/_type/_tParamter.py
thinker/resource_packer/_type/_tTensor.py
thinker/resource_packer/ops/BatchNorm2dInt.py
thinker/resource_packer/ops/Binary_ElementWise_Ops.py
thinker/resource_packer/ops/BmmInt.py
thinker/resource_packer/ops/Cast.py
thinker/resource_packer/ops/Clip.py
thinker/resource_packer/ops/Concat.py
thinker/resource_packer/ops/Constant.py
thinker/resource_packer/ops/ConstantOfShape.py
thinker/resource_packer/ops/Conv1dInt.py
thinker/resource_packer/ops/Conv2dInt.py
pythinker-2.1.1.dist-info/LICENSE
pythinker-2.1.1.dist-info/METADATA
pythinker-2.1.1.dist-info/WHEEL
pythinker-2.1.1.dist-info/entry_points.txt
pythinker-2.1.1.dist-info/top_level.txt
pythinker-2.1.1.dist-info/RECORD
