Metadata-Version: 2.1
Name: pythinker
Version: 2.1.1
Summary: A DeepLearning inference framework for venus
Home-page: https://github.com/LISTENAI/thinker
Author: listenai
Author-email: lingerthinker@listenai.com
Classifier: Programming Language :: Python :: 3
Classifier: License :: OSI Approved :: Apache Software License
Classifier: Operating System :: OS Independent
Requires-Python: >=3.6
License-File: LICENSE
Requires-Dist: onnx
